Arquivos/MariaCarolinaResendeJaudacy_667477_Guia9/clock.v
// -------------------------
// Gerador de Clock
// Nome: Maria Carolina Resende Jaudacy
// Matricula: 667477
// -------------------------

module clock ( output clk );
reg clk;
initial
 begin
 clk = 1'b0;
 end
always
 begin
 #12 clk = ~clk;
 end
endmodule

Arquivos/MariaCarolinaResendeJaudacy_667477_Guia9/Exemplo_0905.v
// -------------------------
// Gerador de pulsos
// Nome: Maria Carolina Resende Jaudacy
// Matricula: 667477
// -------------------------

`include "clock.v"
module pulse ( signal, clock );
input clock;
output signal;
reg signal;
always @ ( posedge clock )
 begin
 signal = 1'b1;
 #48 signal = 1'b0;
 #48 signal = 1'b1;
 #48 signal = 1'b0;
 end
endmodule // pulse

module Exemplo_0905;
wire clock;
clock clk ( clock );
wire p;
pulse pls ( p, clock );
initial begin
 $dumpfile ( "Exemplo0905.vcd" );
 $dumpvars ( 1, clock, p );
 #480 $finish;
end
endmodule // Exemplo_0905

Arquivos/MariaCarolinaResendeJaudacy_667477_Guia9/Exemplo0905.vcd
$date
	Mon Oct 21 15:20:11 2019
$end
$version
	Icarus Verilog
$end
$timescale
	1s
$end
$scope module Exemplo_0905 $end
$var wire 1 ! clock $end
$upscope $end
$scope module Exemplo_0905 $end
$var wire 1 " p $end
$upscope $end
$enddefinitions $end
#0
$dumpvars
x"
0!
$end
#12
1"
1!
#24
0!
#36
1!
#48
0!
#60
1!
0"
#72
0!
#84
1!
#96
0!
#108
1!
1"
#120
0!
#132
1!
#144
0!
#156
1!
1"
#168
0!
#180
1!
#192
0!
#204
1!
0"
#216
0!
#228
1!
#240
0!
#252
1!
1"
#264
0!
#276
1!
#288
0!
#300
1!
1"
#312
0!
#324
1!
#336
0!
#348
1!
0"
#360
0!
#372
1!
#384
0!
#396
1!
1"
#408
0!
#420
1!
#432
0!
#444
1!
1"
